<?xml version="1.0" encoding="UTF-8"?>
<MF0 version="1.1" packageUris="http://schema.mathworks.com/mf0/ci/19700101 http://schema.mathworks.com/mf0/sl_modelref_info/R2024b http://schema.mathworks.com/mf0/slexec_mm_sto/R2024a_202305081229 http://schema.mathworks.com/mf0/sltp_mm/R2024b_202402211119">
  <ModelRefInfoRepo.ModelRefInfoRoot type="ModelRefInfoRepo.ModelRefInfoRoot" uuid="20bbc1b4-d448-4bbc-8740-ff8dae04f4b7">
    <childModelRefInfo type="ModelRefInfoRepo.ChildModelRefInfo" uuid="6f82653f-fa54-4e27-b0dd-72be5babd6d0">
      <modelName>HOST</modelName>
      <modelPath>HOST</modelPath>
    </childModelRefInfo>
    <compDerivCacheNeedsReset>false</compDerivCacheNeedsReset>
    <compZcCacheNeedsReset>false</compZcCacheNeedsReset>
    <compiledTFinal>inf</compiledTFinal>
    <dataSourceInfo type="ModelRefInfoRepo.DataSourceInfo" uuid="cebf4254-5c81-4a73-86ae-7537b0c62700">
      <dataSources type="ModelRefInfoRepo.SourceInfo" uuid="2e4b2de5-94e6-41ad-be70-e38f69344d43">
        <includeAllSections>true</includeAllSections>
        <sourceName>base workspace</sourceName>
        <type>BaseWorkspace</type>
      </dataSources>
      <modelName>HOST</modelName>
    </dataSourceInfo>
    <dataTransferInfos>AAFJTQAAAAAOAAAAOAAAAAYAAAAIAAAAAgAAAAAAAAAFAAAACAAAAAAAAAABAAAAAQAAAAAAAAAFAAQAAQAAAAEAAAAAAAAA</dataTransferInfos>
    <defaultsCMapping>{&quot;Inports&quot;:&quot;{\&quot;Name\&quot;:\&quot;Default\&quot;,\&quot;Checksum\&quot;:\&quot;Default\&quot;,\&quot;PerInstancePropertiesChecksum\&quot;:\&quot;\&quot;,\&quot;MemorySectionName\&quot;:\&quot;\&quot;,\&quot;MemorySectionChecksum\&quot;:\&quot;\&quot;}&quot;,&quot;Outports&quot;:&quot;{\&quot;Name\&quot;:\&quot;Default\&quot;,\&quot;Checksum\&quot;:\&quot;Default\&quot;,\&quot;PerInstancePropertiesChecksum\&quot;:\&quot;\&quot;,\&quot;MemorySectionName\&quot;:\&quot;\&quot;,\&quot;MemorySectionChecksum\&quot;:\&quot;\&quot;}&quot;,&quot;ParameterArguments&quot;:&quot;{\&quot;Name\&quot;:\&quot;Default\&quot;,\&quot;Checksum\&quot;:\&quot;Default\&quot;,\&quot;PerInstancePropertiesChecksum\&quot;:\&quot;\&quot;,\&quot;MemorySectionName\&quot;:\&quot;None\&quot;,\&quot;MemorySectionChecksum\&quot;:\&quot;None\&quot;}&quot;,&quot;LocalParameters&quot;:&quot;{\&quot;Name\&quot;:\&quot;Default\&quot;,\&quot;Checksum\&quot;:\&quot;Default\&quot;,\&quot;PerInstancePropertiesChecksum\&quot;:\&quot;\&quot;,\&quot;MemorySectionName\&quot;:\&quot;\&quot;,\&quot;MemorySectionChecksum\&quot;:\&quot;\&quot;}&quot;,&quot;GlobalParameters&quot;:&quot;{\&quot;Name\&quot;:\&quot;Default\&quot;,\&quot;Checksum\&quot;:\&quot;Default\&quot;,\&quot;PerInstancePropertiesChecksum\&quot;:\&quot;\&quot;,\&quot;MemorySectionName\&quot;:\&quot;\&quot;,\&quot;MemorySectionChecksum\&quot;:\&quot;\&quot;}&quot;,&quot;InternalData&quot;:&quot;{\&quot;Name\&quot;:\&quot;Default\&quot;,\&quot;Checksum\&quot;:\&quot;Default\&quot;,\&quot;PerInstancePropertiesChecksum\&quot;:\&quot;\&quot;,\&quot;MemorySectionName\&quot;:\&quot;\&quot;,\&quot;MemorySectionChecksum\&quot;:\&quot;\&quot;}&quot;,&quot;SharedLocalDataStores&quot;:&quot;{\&quot;Name\&quot;:\&quot;Default\&quot;,\&quot;Checksum\&quot;:\&quot;Default\&quot;,\&quot;PerInstancePropertiesChecksum\&quot;:\&quot;\&quot;,\&quot;MemorySectionName\&quot;:\&quot;None\&quot;,\&quot;MemorySectionChecksum\&quot;:\&quot;None\&quot;}&quot;,&quot;GlobalDataStores&quot;:&quot;{\&quot;Name\&quot;:\&quot;Default\&quot;,\&quot;Checksum\&quot;:\&quot;Default\&quot;,\&quot;PerInstancePropertiesChecksum\&quot;:\&quot;\&quot;,\&quot;MemorySectionName\&quot;:\&quot;None\&quot;,\&quot;MemorySectionChecksum\&quot;:\&quot;None\&quot;}&quot;,&quot;Constants&quot;:&quot;{\&quot;Name\&quot;:\&quot;Default\&quot;,\&quot;Checksum\&quot;:\&quot;Default\&quot;,\&quot;PerInstancePropertiesChecksum\&quot;:\&quot;\&quot;,\&quot;MemorySectionName\&quot;:\&quot;\&quot;,\&quot;MemorySectionChecksum\&quot;:\&quot;\&quot;}&quot;,&quot;DataTransfers&quot;:&quot;{\&quot;Name\&quot;:\&quot;Default\&quot;,\&quot;Checksum\&quot;:\&quot;Default\&quot;,\&quot;PerInstancePropertiesChecksum\&quot;:\&quot;\&quot;,\&quot;MemorySectionName\&quot;:\&quot;None\&quot;,\&quot;MemorySectionChecksum\&quot;:\&quot;None\&quot;}&quot;,&quot;ModelData&quot;:&quot;{\&quot;Name\&quot;:\&quot;Default\&quot;,\&quot;Checksum\&quot;:\&quot;Default\&quot;,\&quot;PerInstancePropertiesChecksum\&quot;:\&quot;\&quot;,\&quot;MemorySectionName\&quot;:\&quot;None\&quot;,\&quot;MemorySectionChecksum\&quot;:\&quot;None\&quot;}&quot;,&quot;InitializeTerminate&quot;:&quot;{\&quot;Name\&quot;:\&quot;Default\&quot;,\&quot;Checksum\&quot;:\&quot;Default\&quot;,\&quot;PerInstancePropertiesChecksum\&quot;:\&quot;\&quot;,\&quot;MemorySectionName\&quot;:\&quot;\&quot;,\&quot;MemorySectionChecksum\&quot;:\&quot;\&quot;}&quot;,&quot;Execution&quot;:&quot;{\&quot;Name\&quot;:\&quot;Default\&quot;,\&quot;Checksum\&quot;:\&quot;Default\&quot;,\&quot;PerInstancePropertiesChecksum\&quot;:\&quot;\&quot;,\&quot;MemorySectionName\&quot;:\&quot;\&quot;,\&quot;MemorySectionChecksum\&quot;:\&quot;\&quot;}&quot;,&quot;SharedUtility&quot;:&quot;{\&quot;Name\&quot;:\&quot;Default\&quot;,\&quot;Checksum\&quot;:\&quot;Default\&quot;,\&quot;PerInstancePropertiesChecksum\&quot;:\&quot;\&quot;,\&quot;MemorySectionName\&quot;:\&quot;\&quot;,\&quot;MemorySectionChecksum\&quot;:\&quot;\&quot;}&quot;}</defaultsCMapping>
    <fastestNoncontSigFeedingDerivPorts>-1.0</fastestNoncontSigFeedingDerivPorts>
    <fundamentalSampleTimePeriod>.001</fundamentalSampleTimePeriod>
    <hasBlockWithPeriodicDiscreteSampleTime>true</hasBlockWithPeriodicDiscreteSampleTime>
    <hasBwsAccessed>true</hasBwsAccessed>
    <loggingSaveFormat>2</loggingSaveFormat>
    <maxFreqHz>-1.0</maxFreqHz>
    <needsAbsoluteTime>true</needsAbsoluteTime>
    <numDataInputPorts>0</numDataInputPorts>
    <numLoggableJacobianDStates>0</numLoggableJacobianDStates>
    <runtimeNonFcnCallRateInfos type="ModelRefInfoRepo.RateInfo">
      <compiled>true</compiled>
      <nonFcnCallPartitionName>D1</nonFcnCallPartitionName>
      <period>.001</period>
      <priority>40</priority>
      <rateIdx>0</rateIdx>
    </runtimeNonFcnCallRateInfos>
    <sampleTimeInheritanceRule>2</sampleTimeInheritanceRule>
    <solverStatusFlags>323</solverStatusFlags>
    <timingAndTaskingRegistry>&lt;?xml version=&quot;1.0&quot;?&gt;
&lt;slexec_sto version=&quot;1.1&quot; packageUris=&quot;http://schema.mathworks.com/mf0/slexec_mm_sto/R2024a_202305081229&quot;&gt;
  &lt;sto.Registry type=&quot;sto.Registry&quot; uuid=&quot;2bb442f7-70e4-44f6-ba4c-5da278163382&quot;&gt;
    &lt;executionSpec&gt;Undetermined&lt;/executionSpec&gt;
    &lt;identifier&gt;HOST&lt;/identifier&gt;
    &lt;clockRegistry type=&quot;sto.ClockRegistry&quot; uuid=&quot;826b6a96-b4c4-4fb2-9c9c-862030917e54&quot;&gt;
      &lt;clocks type=&quot;sto.Timer&quot; uuid=&quot;8cad01c3-2725-47a1-ab93-4813b6eddc0c&quot;&gt;
        &lt;computedFundamentalDiscretePeriod&gt;.001&lt;/computedFundamentalDiscretePeriod&gt;
        &lt;fastestDiscreteRate type=&quot;sto.ClassicPeriodicDiscreteRate&quot; uuid=&quot;1f272dea-713d-4907-aa96-fd3ac62d1ba9&quot;/&gt;
        &lt;isDefaultTimer&gt;true&lt;/isDefaultTimer&gt;
        &lt;resolution&gt;.001&lt;/resolution&gt;
        &lt;timeAdvanceMode&gt;FixedStep&lt;/timeAdvanceMode&gt;
        &lt;identifier&gt;HOST::defaultTimer&lt;/identifier&gt;
        &lt;rates type=&quot;sto.ClassicPeriodicDiscreteRate&quot; uuid=&quot;1f272dea-713d-4907-aa96-fd3ac62d1ba9&quot;&gt;
          &lt;annotation&gt;D1&lt;/annotation&gt;
          &lt;clockId&gt;HOST::defaultTimer&lt;/clockId&gt;
          &lt;description&gt;Discrete 1&lt;/description&gt;
          &lt;taskId&gt;_task0&lt;/taskId&gt;
          &lt;rateSpec type=&quot;sto.RateSpec&quot; uuid=&quot;6b9fc99d-45a7-411d-8f94-d09ca3914517&quot;&gt;
            &lt;period&gt;.001&lt;/period&gt;
            &lt;rateType&gt;ClassicPeriodicDiscrete&lt;/rateType&gt;
          &lt;/rateSpec&gt;
        &lt;/rates&gt;
        &lt;baseRate type=&quot;sto.ClassicPeriodicDiscreteRate&quot; uuid=&quot;7a7e4f6e-995f-4c7b-9d48-58b408b6690f&quot;&gt;
          &lt;annotation&gt;D1&lt;/annotation&gt;
          &lt;clockId&gt;HOST::defaultTimer&lt;/clockId&gt;
          &lt;description&gt;Discrete 1&lt;/description&gt;
          &lt;taskId&gt;_task0&lt;/taskId&gt;
          &lt;rateSpec type=&quot;sto.RateSpec&quot; uuid=&quot;5ad7bc2b-1f70-4887-bb7b-d5d0f341296c&quot;&gt;
            &lt;period&gt;.001&lt;/period&gt;
            &lt;rateType&gt;ClassicPeriodicDiscrete&lt;/rateType&gt;
          &lt;/rateSpec&gt;
        &lt;/baseRate&gt;
      &lt;/clocks&gt;
      &lt;timeAdvanceMode&gt;FixedStep&lt;/timeAdvanceMode&gt;
    &lt;/clockRegistry&gt;
    &lt;taskRegistry type=&quot;sto.TaskRegistry&quot; uuid=&quot;e985c2ff-d907-4a64-94df-f12f365e51f1&quot;&gt;
      &lt;rootTaskHierarchyElements type=&quot;sto.Task&quot; uuid=&quot;0ab51621-8496-45a3-a704-8ac196519d6a&quot;&gt;
        &lt;isExecutable&gt;true&lt;/isExecutable&gt;
        &lt;orderIndex&gt;1&lt;/orderIndex&gt;
        &lt;rates type=&quot;sto.ClassicPeriodicDiscreteRate&quot; uuid=&quot;1a1e60fd-be5f-4796-aaf9-5126cfc87363&quot;&gt;
          &lt;annotation&gt;D1&lt;/annotation&gt;
          &lt;clockId&gt;HOST::defaultTimer&lt;/clockId&gt;
          &lt;description&gt;Discrete 1&lt;/description&gt;
          &lt;taskId&gt;_task0&lt;/taskId&gt;
          &lt;rateSpec type=&quot;sto.RateSpec&quot; uuid=&quot;a72602f6-6f0d-4f8f-bfff-e91068a3c50d&quot;&gt;
            &lt;period&gt;.001&lt;/period&gt;
            &lt;rateType&gt;ClassicPeriodicDiscrete&lt;/rateType&gt;
          &lt;/rateSpec&gt;
        &lt;/rates&gt;
        &lt;schedulingClockId&gt;HOST::defaultTimer&lt;/schedulingClockId&gt;
        &lt;timeKeeperClockId&gt;HOST::defaultTimer&lt;/timeKeeperClockId&gt;
        &lt;elementType&gt;Task&lt;/elementType&gt;
        &lt;identifier&gt;_task0&lt;/identifier&gt;
        &lt;priority&gt;40&lt;/priority&gt;
      &lt;/rootTaskHierarchyElements&gt;
      &lt;taskDependencyGraph type=&quot;sto.SerializedTaskConnectionList&quot; uuid=&quot;b2250655-5bb9-4d23-a15d-aec68290dc90&quot;&gt;
        &lt;clockIdentifier&gt;HOST::defaultTimer&lt;/clockIdentifier&gt;
        &lt;taskIdentifier&gt;_task0&lt;/taskIdentifier&gt;
      &lt;/taskDependencyGraph&gt;
      &lt;taskPriorityDirection&gt;HighNumberLast&lt;/taskPriorityDirection&gt;
    &lt;/taskRegistry&gt;
  &lt;/sto.Registry&gt;
&lt;/slexec_sto&gt;</timingAndTaskingRegistry>
    <userSpecifiedFixedStepSize>.001</userSpecifiedFixedStepSize>
    <FMUBlockMap type="ModelRefInfoRepo.FMUBlockInfo" uuid="05f5972e-3e0b-4f79-88af-e600ee6d98d4"/>
    <codeGenInfo type="ModelRefInfoRepo.CodeGenInformation" uuid="c9f07172-f785-4942-877d-1e0b2c167fdb"/>
    <compiledVariantInfos type="ModelRefInfoRepo.CompiledVariantInfoMap" uuid="6f3f9e20-5226-42fd-a752-3f1adddcefb9"/>
    <configSettingsForConsistencyChecks type="ModelRefInfoRepo.ConfigSettingsForConsistencyChecks" uuid="e283410c-2435-42a8-8f12-99f8475e6d19">
      <consistentOutportInitialization>true</consistentOutportInitialization>
      <fixedStepSize>.001</fixedStepSize>
      <frameDiagnosticSetting>2</frameDiagnosticSetting>
      <hasHybridSampleTime>true</hasHybridSampleTime>
      <signalLoggingSaveFormat>2</signalLoggingSaveFormat>
      <simSIMDOptimization>1</simSIMDOptimization>
      <solverName>FixedStepDiscrete</solverName>
      <solverType>SOLVER_TYPE_FIXEDSTEP</solverType>
      <hardwareSettings type="ModelRefInfoRepo.HardwareSettings" uuid="2359f505-427a-4e28-9364-c9b393574f6b">
        <prodBitPerChar>8</prodBitPerChar>
        <prodBitPerDouble>64</prodBitPerDouble>
        <prodBitPerFloat>32</prodBitPerFloat>
        <prodBitPerInt>32</prodBitPerInt>
        <prodBitPerLong>32</prodBitPerLong>
        <prodBitPerLongLong>64</prodBitPerLongLong>
        <prodBitPerPointer>64</prodBitPerPointer>
        <prodBitPerPtrDiffT>64</prodBitPerPtrDiffT>
        <prodBitPerShort>16</prodBitPerShort>
        <prodBitPerSizeT>64</prodBitPerSizeT>
        <prodEndianess>1</prodEndianess>
        <prodShiftRight>true</prodShiftRight>
        <prodWordSize>64</prodWordSize>
      </hardwareSettings>
    </configSettingsForConsistencyChecks>
    <controllableInputRatesMap type="ModelRefInfoRepo.VarTsUIDMap" uuid="4f3a0e81-f414-47b0-88ed-80e2ee3ebf89"/>
    <controllableOutputRatesMap type="ModelRefInfoRepo.VarTsUIDMap" uuid="1c38b467-43c2-4fe7-b81b-8f2220c6d385"/>
    <dataPortGroup type="ModelRefInfoRepo.DataPortGroup" uuid="af6fe51b-4f89-444a-8594-3147cb414e2c"/>
    <expFcnUnconnectedDataPortGroup type="ModelRefInfoRepo.DataPortGroup" uuid="4521c594-9f82-4064-a3aa-65a2f84a76ce"/>
    <interfaceParameterInfo type="ModelRefInfoRepo.InterfaceParameterInfo" uuid="63c5081d-f5a8-4d23-b26f-042880257ae4"/>
    <messageInfo type="ModelRefInfoRepo.MessageInformation" uuid="a9484989-403c-4735-9b2d-4204f6ae1f2a"/>
    <methodInfo type="ModelRefInfoRepo.MethodExistenceInfo" uuid="1a6309a9-3cf5-4ef4-b22c-d59d5b3ee07f">
      <hasDisableMethod>true</hasDisableMethod>
      <hasSystemInitializeMethod>true</hasSystemInitializeMethod>
      <hasSystemResetMethod>true</hasSystemResetMethod>
      <hasTerminateMethod>true</hasTerminateMethod>
    </methodInfo>
    <periodicEventPortUnsupportedBlockInfo type="ModelRefInfoRepo.PeriodicEventPortUnsupportedBlockInfo" uuid="5fc955bf-153a-4da6-8d99-894b68744c65"/>
    <portGroupsRequireSameRate type="ModelRefInfoRepo.PortGroupsRequireSameRate" uuid="3c95c458-8dd2-4cc6-828b-0834c6198468">
      <DSMPortGroups type="ModelRefInfoRepo.NameToPortGroupIdxVectMap" uuid="7b777d49-2460-4637-b100-9a12ae931c37"/>
      <GlobalDSMPortGroups type="ModelRefInfoRepo.NameToPortGroupIdxVectMap" uuid="3dcdfdbe-db43-4441-a02d-ec4560a4fe06"/>
      <mergedPortGroups type="ModelRefInfoRepo.NameToPortGroupIdxVectMap" uuid="9663866a-ed5c-4640-b816-8f3633692b78"/>
    </portGroupsRequireSameRate>
    <rateBasedMdlGlobalDSMRateSpec type="ModelRefInfoRepo.GlobalDSMRateSpecMap" uuid="2d5c198d-9fe3-4138-b5d3-4051a71ca309"/>
    <rateSpecOfGlobalDSMAccessedByDescExpFcnMdlMap type="ModelRefInfoRepo.GlobalDSMRateSpecMap" uuid="efc3206e-c5f9-4e5c-965d-0623c41ccb70"/>
    <rootBlockDiagramInterface type="ci.Model" uuid="87bfb391-ba66-48fe-aac0-d65311e7141e">
      <p_RootComponentInterface type="ci.ComponentInterface" uuid="7ecb13b4-77da-4fe8-9c26-5fb28c7b37da">
        <p_Name>HOST</p_Name>
        <p_Type>ROOT</p_Type>
      </p_RootComponentInterface>
    </rootBlockDiagramInterface>
    <simulinkFunctions type="ModelRefInfoRepo.SimulinkFunctions" uuid="bf6ec2ae-0298-4d9a-9f01-05d81974f4ee">
      <compSimulinkFunctionCatalog></compSimulinkFunctionCatalog>
    </simulinkFunctions>
    <sltpContext type="sltp.mm.core.Context" uuid="cf557ce1-04eb-4910-a96a-658fe1e655a6">
      <priorityDirection>HighNumberLast</priorityDirection>
      <defaultEventBehavior type="sltp.mm.core.EventBehavior" uuid="7a51ef8e-89e1-45cf-b4d7-4f0c2efcfea2"/>
      <editorState type="sltp.mm.core.EditorState" uuid="b0a66556-565c-4e20-8f65-d1afd377b15e">
        <isSynchronized>true</isSynchronized>
        <panelState type="sltp.mm.core.EditorPanelState" uuid="1d179979-c907-49ea-a59a-862b26191c24"/>
      </editorState>
      <rootTask type="sltp.mm.core.Task" uuid="7d70e752-a712-495d-9d86-be0ea81fd72d">
        <context type="sltp.mm.core.Context" uuid="cf557ce1-04eb-4910-a96a-658fe1e655a6"/>
        <explicit>false</explicit>
        <name>Default</name>
        <priority>-2147483648</priority>
        <subgraph type="sltp.mm.core.Graph" uuid="948558e8-caee-46ae-a333-7c27e7c7c52b">
          <tasks type="sltp.mm.core.Task" uuid="6a680fed-0692-4aa5-9ac6-d43397f60c0d">
            <context type="sltp.mm.core.Context" uuid="cf557ce1-04eb-4910-a96a-658fe1e655a6"/>
            <explicit>false</explicit>
            <id>1</id>
            <isTimed>true</isTimed>
            <name>D1</name>
            <priority>40</priority>
            <rates type="sltp.mm.core.Rate" uuid="c109e273-fa54-4140-a3de-b7958fa56acb">
              <annotation>D1</annotation>
              <color>-12240129</color>
              <identifier>ClassicPeriodicDiscrete0.0010</identifier>
              <rateIndex>0</rateIndex>
              <rateSpec type="sltp.mm.core.RateSpec">
                <period>.001</period>
              </rateSpec>
              <sti>0</sti>
            </rates>
          </tasks>
        </subgraph>
      </rootTask>
    </sltpContext>
    <stateWriterToOwnerMap type="ModelRefInfoRepo.StateWriterInfo" uuid="9095b821-1d61-4463-83a0-3e1cc8986a90"/>
    <stoClientDataRegistry type="sto.ClientDataRegistry" uuid="e19e2457-0076-4f3c-8073-7c82f5e9d532">
      <dataSets type="sto.ClientClockNamedDataSet" uuid="bea07295-143f-4816-855f-dcf1bbeb8e1c">
        <tag>sltpEvents</tag>
      </dataSets>
      <dataSets type="sto.ClientTaskHierarchyElementNamedDataSet" uuid="62ba682c-38e8-45b9-9a50-be79f42e98e6">
        <tag>sltpTaskGroups</tag>
      </dataSets>
      <dataSets type="sto.ClientTaskHierarchyElementNamedDataSet" uuid="71a1ce69-6b05-46ff-9fb7-fe1681867ded">
        <dSet type="ModelRefInfoRepo.SltpTaskData" uuid="6057b9be-fbdc-4df0-87da-e4daf0688fdb"/>
        <tSet type="ModelRefInfoRepo.SltpTaskData" uuid="6057b9be-fbdc-4df0-87da-e4daf0688fdb">
          <dataName>D1</dataName>
          <linkedSet type="sto.ClientTaskHierarchyElementNamedDataSet" uuid="71a1ce69-6b05-46ff-9fb7-fe1681867ded"/>
          <id type="sto.TaskHierarchyElementId">
            <clockId>HOST::defaultTimer</clockId>
            <id>_task0</id>
          </id>
        </tSet>
        <tag>sltpTasks</tag>
      </dataSets>
    </stoClientDataRegistry>
    <typeTable type="type_info.TypeTable" uuid="9d486c2a-3a98-4248-bfe8-bddfd1bd1bb6">
      <Types type="type_info.Type" uuid="875e5898-5ee1-4db1-b059-a708f1738bb8">
        <DataTypeId>12</DataTypeId>
        <Size>8</Size>
        <Name>action</Name>
      </Types>
      <Types type="type_info.NumericType" uuid="bbc96c91-df9f-4dc7-b9f6-9a1d14b64387">
        <DataTypeId>8</DataTypeId>
        <MxClassId>3</MxClassId>
        <Size>1</Size>
        <typeEnum>NUMERIC</typeEnum>
        <Name>boolean</Name>
      </Types>
      <Types type="type_info.NumericType" uuid="0bb48598-303b-44bb-bede-0932ac0c5d70">
        <MxClassId>6</MxClassId>
        <Size>8</Size>
        <typeEnum>NUMERIC</typeEnum>
        <Name>double</Name>
      </Types>
      <Types type="type_info.Type" uuid="e2bd5052-7fa1-4586-b5fc-08219c05d855">
        <DataTypeId>9</DataTypeId>
        <Name>fcn_call</Name>
      </Types>
      <Types type="type_info.NumericType" uuid="4ca59edf-7718-476a-ab6d-f7c17cddeb24">
        <DataTypeId>4</DataTypeId>
        <MxClassId>10</MxClassId>
        <Size>2</Size>
        <typeEnum>NUMERIC</typeEnum>
        <Name>int16</Name>
      </Types>
      <Types type="type_info.NumericType" uuid="e8cf2872-0a0c-472f-8333-20a2cb578619">
        <DataTypeId>6</DataTypeId>
        <MxClassId>12</MxClassId>
        <Size>4</Size>
        <typeEnum>NUMERIC</typeEnum>
        <Name>int32</Name>
      </Types>
      <Types type="type_info.FixedPointType" uuid="611e7402-35ff-48fc-a884-146b504b8615">
        <DataTypeId>15</DataTypeId>
        <Size>8</Size>
        <typeEnum>FIXPOINT</typeEnum>
        <Name>int64</Name>
      </Types>
      <Types type="type_info.NumericType" uuid="63c837b1-bd8e-4cbf-bcc8-668cd0835a55">
        <DataTypeId>2</DataTypeId>
        <MxClassId>8</MxClassId>
        <Size>1</Size>
        <typeEnum>NUMERIC</typeEnum>
        <Name>int8</Name>
      </Types>
      <Types type="type_info.Type" uuid="9fbe237f-e8e0-4805-9007-ce21f622c556">
        <DataTypeId>10</DataTypeId>
        <MxClassId>12</MxClassId>
        <Size>4</Size>
        <Name>integer</Name>
      </Types>
      <Types type="type_info.Type" uuid="1e75a5e5-4792-49fa-ba0d-64c45959cbca">
        <DataTypeId>14</DataTypeId>
        <Size>8</Size>
        <Name>physical_connection</Name>
      </Types>
      <Types type="type_info.Type" uuid="04ba171d-bf02-4140-bae4-c0b92c56c05f">
        <DataTypeId>11</DataTypeId>
        <Size>8</Size>
        <Name>pointer</Name>
      </Types>
      <Types type="type_info.Type" uuid="8063067a-61b2-44b3-8e14-48f5810c0707">
        <DataTypeId>18</DataTypeId>
        <Size>16</Size>
        <Name>sdAmwXbnJnEmimT0NaJRtAD2</Name>
      </Types>
      <Types type="type_info.NumericType" uuid="02cb7207-919c-4a3a-8c69-9b024547fb89">
        <DataTypeId>1</DataTypeId>
        <MxClassId>7</MxClassId>
        <Size>4</Size>
        <typeEnum>NUMERIC</typeEnum>
        <Name>single</Name>
      </Types>
      <Types type="type_info.Type" uuid="ce52bafc-222c-4909-aff6-f8bcbc9e24ec">
        <DataTypeId>19</DataTypeId>
        <Size>256</Size>
        <Name>system_SerialConfiguration3</Name>
      </Types>
      <Types type="type_info.Type" uuid="c49ec859-4534-4798-a98b-35b69e1fafd1">
        <DataTypeId>17</DataTypeId>
        <Size>424</Size>
        <Name>system_SerialReceive1</Name>
      </Types>
      <Types type="type_info.Type" uuid="70d8e5ff-9aaa-4c19-af2f-631d1d991f28">
        <DataTypeId>13</DataTypeId>
        <Size>8</Size>
        <Name>timer_uint32_pair</Name>
      </Types>
      <Types type="type_info.NumericType" uuid="ab46ea65-5a79-4474-b8f3-e53ebd4516b0">
        <DataTypeId>5</DataTypeId>
        <MxClassId>11</MxClassId>
        <Size>2</Size>
        <typeEnum>NUMERIC</typeEnum>
        <Name>uint16</Name>
      </Types>
      <Types type="type_info.NumericType" uuid="c22defb9-faaf-487d-a05b-55434b02aca5">
        <DataTypeId>7</DataTypeId>
        <MxClassId>13</MxClassId>
        <Size>4</Size>
        <typeEnum>NUMERIC</typeEnum>
        <Name>uint32</Name>
      </Types>
      <Types type="type_info.FixedPointType" uuid="56532754-d149-4541-83e6-b610d5086b1e">
        <DataTypeId>16</DataTypeId>
        <Size>8</Size>
        <typeEnum>FIXPOINT</typeEnum>
        <Name>uint64</Name>
      </Types>
      <Types type="type_info.NumericType" uuid="e72ca73a-eb2d-4147-a870-af449077eaca">
        <DataTypeId>3</DataTypeId>
        <MxClassId>9</MxClassId>
        <Size>1</Size>
        <typeEnum>NUMERIC</typeEnum>
        <Name>uint8</Name>
      </Types>
      <isInitialized>true</isInitialized>
    </typeTable>
    <varTsUIDMap type="ModelRefInfoRepo.VarTsUIDMap" uuid="53262acb-bba9-46ec-8927-f4ccd6746420"/>
  </ModelRefInfoRepo.ModelRefInfoRoot>
</MF0>